models/__init__.py
models/search_results.py
utils/__init__.py
utils/logger.py
utils/api/__init__.py
utils/api/shopify_client.py
shopify_predictive_search-0.1.3.dist-info/METADATA
shopify_predictive_search-0.1.3.dist-info/WHEEL
shopify_predictive_search-0.1.3.dist-info/entry_points.txt
shopify_predictive_search-0.1.3.dist-info/top_level.txt
shopify_predictive_search-0.1.3.dist-info/RECORD
